LICENSE.md
MANIFEST.in
README.md
setup.cfg
setup.py
mamonca/cMC.cpp
mamonca/cMC.h
mamonca/cMC.pxd
mamonca/mc.pyx
mamonca.egg-info/PKG-INFO
mamonca.egg-info/SOURCES.txt
mamonca.egg-info/dependency_links.txt
mamonca.egg-info/top_level.txt
tests/test_full_run.py
tests/test_heisenberg.py
tests/test_landau.py