Metadata-Version: 2.1
Name: mamonca
Version: 0.0.8
Summary: mamonca - interactive Magnetic Monte Carlo code
Home-page: https://github.com/samwaseda/mamonca
Author: Sam Waseda
Author-email: waseda@mpie.de
License: BSD
License-File: LICENSE.md
